tabpfn/__init__.py
tabpfn/base.py
tabpfn/classifier.py
tabpfn/constants.py
tabpfn/errors.py
tabpfn/inference.py
tabpfn/inference_config.py
tabpfn/inference_tuning.py
tabpfn/model_loading.py
tabpfn/parallel_execute.py
tabpfn/regressor.py
tabpfn/settings.py
tabpfn/utils.py
tabpfn/validation.py
tabpfn/architectures/__init__.py
tabpfn/architectures/interface.py
tabpfn/architectures/base/__init__.py
tabpfn/architectures/base/bar_distribution.py
tabpfn/architectures/base/config.py
tabpfn/architectures/base/layer.py
tabpfn/architectures/base/memory.py
tabpfn/architectures/base/mlp.py
tabpfn/architectures/base/tabpfn_col_embedding.pt
tabpfn/architectures/base/thinking_tokens.py
tabpfn/architectures/base/transformer.py
tabpfn/architectures/base/attention/__init__.py
tabpfn/architectures/base/attention/full_attention.py
tabpfn/architectures/encoders/__init__.py
tabpfn/architectures/encoders/pipeline_interfaces.py
tabpfn/architectures/encoders/steps/__init__.py
tabpfn/architectures/encoders/steps/_ops.py
tabpfn/architectures/encoders/steps/feature_group_projections_encoder_step.py
tabpfn/architectures/encoders/steps/feature_transform_encoder_step.py
tabpfn/architectures/encoders/steps/frequency_feature_encoder_step.py
tabpfn/architectures/encoders/steps/multiclass_classification_target_encoder_step.py
tabpfn/architectures/encoders/steps/nan_handling_encoder_step.py
tabpfn/architectures/encoders/steps/normalize_feature_groups_encoder_step.py
tabpfn/architectures/encoders/steps/remove_duplicate_features_encoder_step.py
tabpfn/architectures/encoders/steps/remove_empty_features_encoder_step.py
tabpfn/finetuning/__init__.py
tabpfn/finetuning/_torch_compat.py
tabpfn/finetuning/data_util.py
tabpfn/finetuning/finetuned_base.py
tabpfn/finetuning/finetuned_classifier.py
tabpfn/finetuning/finetuned_regressor.py
tabpfn/finetuning/train_util.py
tabpfn/misc/_sklearn_compat.py
tabpfn/misc/debug_versions.py
tabpfn/model/__init__.py
tabpfn/model/attention.py
tabpfn/model/bar_distribution.py
tabpfn-6.3.2.dist-info/licenses/LICENSE
tabpfn-6.3.2.dist-info/METADATA
tabpfn-6.3.2.dist-info/WHEEL
tabpfn-6.3.2.dist-info/top_level.txt
tabpfn-6.3.2.dist-info/RECORD
